umvlib/Constants.py
umvlib/Fields.py
umvlib/__init__.py
umvlib/new_test.py
umvlib/umv.py
umvlib/processed/2022-10-06 08:19:32.283250_Aprovar (75).csv
umvlib/processed/Aprovar (74).csv
umvlib-0.0.7.dist-info/METADATA
umvlib-0.0.7.dist-info/WHEEL
umvlib-0.0.7.dist-info/licenses/LICENSE
umvlib-0.0.7.dist-info/RECORD
