Metadata-Version: 2.1
Name: umvlib
Version: 0.0.7
Summary: Umov API sdk
Author-email: Ademir Queiroga <ademirneto2007@gmail.com>
License-File: LICENSE
Classifier: Programming Language :: Python :: 3
Requires-Python: >=3.7
Requires-Dist: requests
